djangocms_column/__init__.py
djangocms_column/cms_plugins.py
djangocms_column/forms.py
djangocms_column/models.py
djangocms_column/locale/af/LC_MESSAGES/django.mo
djangocms_column/locale/af/LC_MESSAGES/django.po
djangocms_column/locale/ar/LC_MESSAGES/django.mo
djangocms_column/locale/ar/LC_MESSAGES/django.po
djangocms_column/locale/be/LC_MESSAGES/django.mo
djangocms_column/locale/be/LC_MESSAGES/django.po
djangocms_column/locale/bg/LC_MESSAGES/django.mo
djangocms_column/locale/bg/LC_MESSAGES/django.po
djangocms_column/locale/bn/LC_MESSAGES/django.mo
djangocms_column/locale/bn/LC_MESSAGES/django.po
djangocms_column/locale/ca/LC_MESSAGES/django.mo
djangocms_column/locale/ca/LC_MESSAGES/django.po
djangocms_column/locale/cmn/LC_MESSAGES/django.mo
djangocms_column/locale/cmn/LC_MESSAGES/django.po
djangocms_column/locale/cs/LC_MESSAGES/django.mo
djangocms_column/locale/cs/LC_MESSAGES/django.po
djangocms_column/locale/cy/LC_MESSAGES/django.mo
djangocms_column/locale/cy/LC_MESSAGES/django.po
djangocms_column/locale/da/LC_MESSAGES/django.mo
djangocms_column/locale/da/LC_MESSAGES/django.po
djangocms_column/locale/de/LC_MESSAGES/django.mo
djangocms_column/locale/de/LC_MESSAGES/django.po
djangocms_column/locale/el/LC_MESSAGES/django.mo
djangocms_column/locale/el/LC_MESSAGES/django.po
djangocms_column/locale/en/LC_MESSAGES/django.mo
djangocms_column/locale/en/LC_MESSAGES/django.po
djangocms_column/locale/es/LC_MESSAGES/django.mo
djangocms_column/locale/es/LC_MESSAGES/django.po
djangocms_column/locale/es_AR/LC_MESSAGES/django.mo
djangocms_column/locale/es_AR/LC_MESSAGES/django.po
djangocms_column/locale/es_BO/LC_MESSAGES/django.mo
djangocms_column/locale/es_BO/LC_MESSAGES/django.po
djangocms_column/locale/es_DO/LC_MESSAGES/django.mo
djangocms_column/locale/es_DO/LC_MESSAGES/django.po
djangocms_column/locale/et/LC_MESSAGES/django.mo
djangocms_column/locale/et/LC_MESSAGES/django.po
djangocms_column/locale/eu/LC_MESSAGES/django.mo
djangocms_column_fork-1.7.2.dist-info/DESCRIPTION.rst
djangocms_column_fork-1.7.2.dist-info/METADATA
djangocms_column_fork-1.7.2.dist-info/RECORD
djangocms_column_fork-1.7.2.dist-info/WHEEL
djangocms_column_fork-1.7.2.dist-info/metadata.json
djangocms_column_fork-1.7.2.dist-info/top_level.txt
